{
  "name": "Pitch Perfect 3",
  "year": 2017,
  "runtime": 93,
  "categories": [
    "comedy",
    "music"
  ],
  "release-date": "2017-12-21",
  "director": "Trish Sie",
  "writer": [
    "Kay Cannon",
    "Mike White"
  ],
  "actors": [
    "Anna Kendrick",
    "Rebel Wilson",
    "Brittany Snow",
    "Anna Camp",
    "Hailee Steinfeld",
    "Ester Dean",
    "Hana Mae Lee",
    "Kelley Jakle",
    "Shelley Regner",
    "Chrissie Fit",
    "Elizabeth Banks",
    "John Michael Higgins",
    "John Lithgow",
    "Matt Lanter",
    "Guy Burnet"
  ],
  "storyline": "After the highs of winning the World Championships, the Bellas find themselves split apart and discovering there aren't job prospects for making music with your mouth. But when they get the chance to reunite for an overseas USO tour, this group of awesome nerds will come together to make some music, and some questionable decisions, one last time.\n\n"
}
