{
	"name": "Twin Peaks: Fire Walk With Me",
	"year": 1992,
	"runtime": 134,
	"categories": [
	"drama",
	"horror",
	"mystery"
	],
	"release-date": "1992-08-28" ,
	"director": "david lynch",
	"writer": [
	"david lynch",
	"robert engels"	
	],
	"actors": [
	"sheryl lee",
	"ray wise",
	"dana ashbrook",
	"phoebe augustine",
	"david bowie",
	"eric dare",
	"miguel ferrer",
	"pamela gidley",
	"heather graham",
	"chris isaak",
	"moira kelly",
	"peggy lipton",
	"david lynch",
	"james marshall"
	],
	"storyline": "essentially a prequel to david lynch and mark frost's earlier TV series 'Twin Peaks'. the first hour or so concerns the investigation by FBI Agent Chet Desmond and his partner Sam Stanley int o the murder of night-shift waitress Teresa Banks in the small Washing state town of Deer Meadow. When Desmond find a mysterious clue to the murder, he inexplicably disappears. The film then cuts to one year later in the nearby town of Twin Peaks and follows the events during the last week in the life of Laura Palmer a troubled teenage girl with two boyfrieds; the hot-tempered rebel Bobby Briggs and quiet biker James Hurley, her drug addiction, and her relationship with her difficult father Leland, a story in which her violent murder was later to motivate much of the TV series. Contains a considerable amount of sex, drugs, violence, very loud music and inexplicable imagery."
}
