{
    "name": "A Quiet Place",
    "year": 2018,
    "runtime": 90,
    "categories": [
      "horror",
      "thriller"
    ],
    "release-date": "2018-03-09",
    "director": "John Krasinski",
    "writer": [
        "Bryan Woods",
        "Scott Beck",
        "John Krasinski"
    ],
    "actors": [
        "Emily Blunt",
        "John Krasinski",
        "Millicent Simmonds", 
        "Noah Jupe"
    ],
    "storyline": "A family is forced to live in silence while hiding from creatures that hunt by sound."
  }
  