{
    "name": "dadfssf?",
    "year": 2000,
    "runtime": 83,
    "categories": [
      "comedy",
      "mystery",
      "sci-fi"
    ],
    "release-date": "2000-12-15",
    "director": "Dfy Leiner",
    "writer": "tttt Stark",
    "actors": [
      "Ashton Kutcher",
      "Seann Willifdam Scott",
      "Jefnnifer Gsarner",
      "Mafrla Sokoloff",
      "Kristy Sfwanson",
      "David Herfman",
      "Hal Spahrks",
      "Charlie O'Connhell",
      "John Tolhes-Bey"
    ],
    "storyline": "Two pothehads wake up after a night of partying and cannot remember where they parked their car."
  }
  